extension_maker/__init__.py
extension_maker/__main__.py
extension_maker/config.py
extension_maker/maker.py
extension_maker/ui.py
extension_maker-1.0.4.dist-info/LICENSE
extension_maker-1.0.4.dist-info/METADATA
extension_maker-1.0.4.dist-info/WHEEL
extension_maker-1.0.4.dist-info/entry_points.txt
extension_maker-1.0.4.dist-info/top_level.txt
extension_maker-1.0.4.dist-info/RECORD
